fdbt/__init__.py
fdbt/cli.py
fdbt-0.1.0.dist-info/licenses/LICENSE
fdbt-0.1.0.dist-info/METADATA
fdbt-0.1.0.dist-info/WHEEL
fdbt-0.1.0.dist-info/entry_points.txt
fdbt-0.1.0.dist-info/top_level.txt
fdbt-0.1.0.dist-info/RECORD
