Metadata-Version: 2.4
Name: fdbt
Version: 0.1.0
Summary: Fast dbt - We implement dbt commands just way faster coming soon
Author-email: TensorStax <info@tensorstax.com>
License: MIT License
Project-URL: Homepage, https://github.com/tensorstax/fdbt
Project-URL: Issues, https://github.com/tensorstax/fdbt/issues
Classifier: Development Status :: 3 - Alpha
Classifier: Intended Audience :: Developers
Classifier: License :: OSI Approved :: MIT License
Classifier: Programming Language :: Python :: 3
Classifier: Programming Language :: Python :: 3.7
Classifier: Programming Language :: Python :: 3.8
Classifier: Programming Language :: Python :: 3.9
Classifier: Programming Language :: Python :: 3.10
Classifier: Programming Language :: Python :: 3.11
Classifier: Programming Language :: Python :: 3.12
Requires-Python: >=3.7
License-File: LICENSE
Dynamic: license-file
